ondewo/__init__.py
ondewo/s2t/__init__.py
ondewo/s2t/speech_to_text_pb2.py
ondewo/s2t/speech_to_text_pb2.pyi
ondewo/s2t/speech_to_text_pb2_grpc.py
ondewo/s2t/client/__init__.py
ondewo/s2t/client/async_client.py
ondewo/s2t/client/async_services_container.py
ondewo/s2t/client/client.py
ondewo/s2t/client/client_config.py
ondewo/s2t/client/services_container.py
ondewo/s2t/client/services/__init__.py
ondewo/s2t/client/services/async_speech_to_text.py
ondewo/s2t/client/services/speech_to_text.py
ondewo_s2t_client-7.0.0.dist-info/LICENSE
ondewo_s2t_client-7.0.0.dist-info/METADATA
ondewo_s2t_client-7.0.0.dist-info/WHEEL
ondewo_s2t_client-7.0.0.dist-info/top_level.txt
ondewo_s2t_client-7.0.0.dist-info/RECORD
